<?xml version="1.0" encoding="utf-8"?>
<resources>
    <string name="mes_abril">April</string>
    <string name="gasto_accidente">Unfall</string>
    <string name="gasto_accesorios">Zubehör und Tuning</string>
    <string name="mantenimiento_refrigerante_radiador">Kühlerfrost</string>
    <string name="accion_aceptar">Sichern</string>
    <string name="texto_vehiculo">Fahrzeug</string>
    <string name="mes_agosto">August</string>
    <string name="accion_nueva">Neu</string>
    <string name="accion_nuevo">Neu</string>
    <string name="limpieza_agua_osmotizada">Osmotischen wasser</string>
    <string name="mantenimiento_aire_acondicionado">Klimaanlage</string>
    <string name="mantenimiento_alineacion_ruedas">Achsvermessung</string>
    <string name="ingreso_alquiler">Miete</string>
    <string name="limpieza_lavadero">Autowaschanlagen</string>
    <string name="mantenimiento_bateria">Batterie</string>
    <string name="texto_primer_vehiculo">Fügen Sie Ihr erstes Fahrzeug</string>
    <string name="texto_primer_lugar">Fügen Sie Ihren ersten Platz</string>
    <string name="mantenimiento_bujia">Zündkerze</string>
    <string name="mensaje_buscando_ubicacion">Die Suche nach Lage</string>
    <string name="mantenimiento_cadena">Kette</string>
    <string name="accion_calcular">Berechnen</string>
    <string name="mensaje_calculadora_precio">Treibstoffpreis \n\n. Hinweis: Dieses Feld wird automatisch mit der Durchschnittspreis von Kraftstoff-Tankstellen, die in der Anwendung erstellt werden besiedelt.</string>
    <string name="mensaje_calculadora_distancia">Gesamtstrecke auf dem Weg gereist</string>
    <string name="mensaje_calculadora_eficiencia">Kraftstoffeffizienz Wert \n\n. Hinweis: Dieses Feld wird automatisch mit der durchschnittlichen Kraftstoffeffizienz, die das Fahrzeug registrieren besiedelt.</string>
    <string name="mensaje_calculadora_error">Die folgenden Informationen werden für die Berechnung erforderlich:</string>
    <string name="mensaje_calculadora_adicional">Gesamtkosten der Extras, die auf der Reise sein wird, wie: Hotels, Verpflegung, etc.</string>
    <string name="mensaje_calculadora_informacion">Mit Reise-Rechner können die Gesamtkosten, die eine Reise, die Sie für Ihr Fahrzeug zu machen, für die Berechnung der Gesamtkosten erzeugen können, sollten Folgendes berücksichtigen zu planen:</string>
    <string name="mensaje_calculadora_nota">Das Ergebnis der Berechnung ist eine Annäherung an den tatsächlichen Wert, der auf der Fahrt generiert wird</string>
    <string name="mensaje_calculadora_peaje">Gesamtkosten der Maut, den Weg der Reise überqueren</string>
    <string name="mensaje_calculadora_titulo">Routenberechnung</string>
    <string name="accion_valoracion">Bewertung</string>
    <string name="accion_cancelar">Abbruch</string>
    <string name="limpieza_cera">Wachs</string>
    <string name="mantenimiento_chasis">Chassis</string>
    <string name="reportes_seleccionar_fechas">Datum wählen</string>
    <string name="reportes_seleccionar_meses">Wählen Sie den Monat und das Jahr</string>
    <string name="reportes_seleccionar_trimestre">Wählen Sie den Zeitraum des Jahres</string>
    <string name="mantenimiento_cinturon">Gürtel</string>
    <string name="texto_clima_invierno">Winter</string>
    <string name="texto_clima_mixto">Gemischt</string>
    <string name="texto_clima_nevado">Schnee</string>
    <string name="texto_clima_verano">Sommer</string>
    <string name="mantenimiento_cojineria">Kissen</string>
    <string name="mantenimiento_sistema_combustible">Kraftstoffsystem</string>
    <string name="mensaje_combustible">Kraftstoff</string>
    <string name="texto_compania_combustible">Kraftstoffunternehmen</string>
    <string name="texto_compania">Unternehmen</string>
    <string name="mensaje_compartir">Ich möchte mit Ihnen diese unglaubliche Anwendung zu teilen, klicken Sie bitte auf den folgenden Link zum Download: http://www.yeikcar.com</string>
    <string name="texto_ruta">Route</string>
    <string name="texto_repostajes">Auftanken</string>
    <string name="texto_hacer_pregunta">Eine frage stellen</string>
    <string name="texto_guardar_dropbox">Sparen Datenbank auf Dropbox</string>
    <string name="accion_continuar">Fortsetzen</string>
    <string name="mensaje_error_subida">Hochgeladene Fehler</string>
    <string name="mensaje_exito_subida">Erfolgreich hochgeladen</string>
    <string name="texto_correo_electronico">E-Mail</string>
    <string name="accion_enlazar">Link</string>
    <string name="mensaje_enlazar_dropbox">Link zu Ihrem Dropbox-Konto</string>
    <string name="mensaje_no_enlace_dropbox">Ihr Konto ist noch nicht verbunden Dropbox</string>
    <string name="mensaje_si_enlace_dropbox">Ihr Konto ist bereits verbunden Dropbox</string>
    <string name="mensaje_enviar_db_correo">Senden Sie die Datenbank per E-Mail</string>
    <string name="texto_copia_seguridad">Sicherungskopie</string>
    <string name="mensaje_detalles_copia_seguridad">Sie können eine Sicherung, die alle Fahrzeugdaten wie Konsumaktivitäten, Wartung, Kosten, Reinigung und Erinnerungen zu speichern wird.</string>
    <string name="mensaje_guardar_db_interno">Sparen Datenbank im internen Speicher</string>
    <string name="texto_fechas">Dates</string>
    <string name="texto_mes_ano">Monat/Jahr</string>

    <string name="texto_numero_dias">Anzahl der Tage</string>
    <string name="texto_por_dia">Pro tag</string>
    <string name="mensaje_borrar_consumo">Löschen füllen</string>
    <string name="mensaje_pregunta_borrar_consumo">Sind Sie sicher, dass Sie diese ausfüllen löschen?</string>
    <string name="mensaje_borrar_gasto">Kosten löschen</string>
    <string name="mensaje_pregunta_borrar_gasto">Sind Sie sicher, Sie wollen diesen Kosten löschen?</string>
    <string name="mensaje_borrar_ingreso">Einkommen löschen</string>
    <string name="mensaje_pregunta_borrar_ingreso">Sind Sie sicher, Sie wollen diesen Einkommen löschen?</string>
    <string name="mensaje_borrar_limpieza">Reinigungs löschen</string>
    <string name="mensaje_pregunta_borrar_limpieza">Sind Sie sicher, Sie wollen diesen Reinigungs löschen?</string>
    <string name="mensaje_borrar_mantenimiento">Wartung löschen</string>
    <string name="mensaje_pregunta_borrar_mantenimiento">Sind Sie sicher, Sie wollen diesen Wartungs löschen?</string>
    <string name="acccion_detalles">Details</string>
    <string name="mes_diciembre">Dezember</string>
    <string name="texto_maximo">Maximum</string>
    <string name="texto_maxima">Maxime</string>
    <string name="texto_minimo">Minimum</string>
    <string name="text_minima">Minimum</string>
    <string name="texto_odometro_">Kilometerstand(</string>
    <string name="texto_distancia_">Entfernung(</string>
    <string name="texto_promedio">Durchschnitt</string>
    <string name="texto_ultimo">letzte</string>
    <string name="texto_ultima">Neueste</string>
    <string name="texto_distancia_total">Gesamtstrecke</string>
    <string name="texto_por_distancia">Nach Entfernung</string>
    <string name="texto_distancia">Distanz</string>
    <string name="texto_memoria_interna">Interner Speicher</string>
    <string name="texto_descargando_copia_seguridad">Herunterladen von Backup</string>
    <string name="dropbox_sincronizacion_automatica">Automatische Synchronisation</string>
    <string name="dropbox_mensaje_sincronizacion">Automatischer Datenabgleich</string>
    <string name="dropbox_notificacion">Benachrichtigung</string>
    <string name="dropbox_mensaje_notificaciones">Benachrichtigungen aktivieren, wenn Informationen an Dropbox senden</string>
    <string name="texto_eficiencia_">Leistungsfähigkeit(</string>
    <string name="mantenimiento_sistema_electrico">Elektrisches System</string>
    <string name="mensaje_copia_seguridad_recuperada">Backup wiederhergestellt</string>
    <string name="mensaje_titulo_copia_seguridad">Backup YeikCar</string>
    <string name="mensaje_resumen_copia_seguridad">Es wird ein neues Backup zu Dropbox erstellen, wird dieser Vorgang nicht frühere Backups gelöscht werden, können Sie weiterhin oder aufheben Ihrem Dropbox-Konto</string>
    <string name="mensaje_recuperar_copia_seguridad">Es wird das letzte Backup in Dropbox gemacht wiederherzustellen, wird dieser Prozess den aktuellen Daten überschrieben, fortfahren möchten Sie?</string>
    <string name="texto_desvincular">Unlink</string>
    <string name="texto_desvincular_dropbox">Unlink Dropbox-Konto</string>
    <string name="accion_enviar">Zukommen Lassen</string>
    <string name="texto_copia_no_recuperada">Backup nicht wiederhergestellt</string>
    <string name="texto_ruta_copia_seguridad">Backup ist in erstellt:</string>
    <string name="mes_enero">Januar</string>


    <string name="mensaje_exportando_basedatos">Datenbank exportieren</string>
    <string name="mantenimiento_retrovisores">Rückspiegel</string>
    <string name="texto_estilo_conduccion">Fahrstil</string>
    <string name="texto_estilo_lento">mäßig</string>
    <string name="texto_estilo_medio">Normal</string>
    <string name="texto_estilo_rapido">Schnell</string>
    <string name="texto_estacion_servicio">Tankstelle</string>
    <string name="accion_exportar">Ausfuhr</string>
    <string name="texto_exportando_archivo">Export-Datei</string>
    <string name="mensaje_exportacion_fallida">Ausfuhr ist fehlgeschlagen</string>
    <string name="mensaje_exportacion_exitosa">Ausfuhr erfolgreich</string>
    <string name="texto_adicional">Extra</string>
    <string name="texto_ingresar_fechas">Sie müssen ein Startdatum und ein Enddatum eingeben</string>
    <string name="texto_base_conocimiento">Wissensbasis</string>
    <string name="mes_febrero">Februar</string>
    <string name="dropbox_recuperar_basedatos">Erholen Datenbank Dropbox</string>
    <string name="texto_recuperar_basedatos">Datenbank wiederherstellen interner Speicher</string>
    <string name="texto_fecha">Datum</string>
    <string name="mantenimiento_fitro_combustible">Kraftstofffilter</string>
    <string name="accion_filtrar">Filter</string>
    <string name="texto_fecha_final">Schlussdatum</string>
    <string name="texto_financiero">finanziell</string>
    <string name="texto_foto_comunidad">Community-Forum</string>
    <string name="mantenimiento_liquido_frenos">Bremsflüssigkeit</string>

    <string name="texto_galones">Gallonen</string>
    <string name="texto_ganacias">Gewinn</string>
    <string name="texto_gastos">Ausgabendetails</string>
    <string name="texto_gastos_totales">Gesamtausgaben</string>
    <string name="texto_costos_">Kosten (</string>
    <string name="texto_general">Allgemein</string>
    <string name="texto_grafica">Grafiken</string>
    <string name="texto_graficas">Grafiken</string>
    <string name="mensaje_fecha_error">Fehler im bucht</string>
    <string name="mensaje_fecha_detalles_error">Das Startdatum kann nicht nach dem Enddatum liegen</string>
    <string name="texto_mes">Monat</string>
    <string name="texto_ano">Jahr</string>
    <string name="texto_periodo_ano">Jahres-Zeitraum</string>
    <string name="mantenimiento_sistema_hidraulico">Hydrauliksystem</string>
    <string name="accion_importar">Import</string>
    <string name="mensaje_importando_archivo">Importieren von Dateien</string>
    <string name="mensaje_importacion_fallida">Import fehlgeschlagen</string>
    <string name="mensaje_importacion_exitosa">Import successful</string>
    <string name="gastos_impuestos">Steuer</string>
    <string name="texto_informacion">Information</string>
    <string name="texto_detalles_calculo">* Die Berechnung des Prozentsatzes wird von den Gesamtkosten eines jeden Monats erhalten</string>
    <string name="texto_ingresos">Einkommen</string>
    <string name="texto_fecha_inicio">Startdatum</string>
    <string name="mensaje_no_conexion_internet">Keine Internetverbindung</string>
    <string name="texto_intervalo">Intervall</string>
    <string name="mes_julio">Juli</string>
    <string name="mes_junio">Juni</string>
    <string name="texto_kilometraje">Kilometerstand</string>
    <string name="limpieza_apresion">Hochdruckreiniger</string>
    <string name="limpieza_lavado_en_seco">Trockenreinigung</string>
    <string name="mensaje_detalles_agradecimiento">Besonderer Dank gilt den folgenden Bibliotheken:</string>
    <string name="mensaje_agradecimiento">Dankbarkeit</string>
    <string name="texto_licencias">Lizenzen</string>
    <string name="mantenimiento_limpia_parabrizas">Scheibenwischer</string>
    <string name="texto_limpiezas">Reinigungen</string>
    <string name="texto_librerias">Bibliotheken</string>
    <string name="texto_detalles_librerias">Bibliotheken in der Anwendung verwendet</string>
    <string name="mantenimiento_llantas">Bereifung</string>
    <string name="mantenimiento_luces">Lichter</string>
    <string name="texto_lugares">Places</string>
    <string name="texto_compania_combustibles">Kraftstoffunternehmen</string>
    <string name="texto_tipo_limpieza">Reinigung Typ</string>
    <string name="limpieza_a_mano">Handwäsche</string>
    <string name="texto_mantenimientos">Wartungen</string>
    <string name="mensaje_ubicacion_mapa">Wenn Sie nicht die automatische Platzierung zu erhalten, können Sie manuell Drücken einer bestimmten Stelle auf der Karte</string>
    <string name="texto_mapa">KARTE</string>
    <string name="mes_marzo">März</string>
    <string name="mes_mayo">Mai</string>
    <string name="mensaje_pregunta_borrar_vehiculo">Sind Sie sicher, dass Sie möchten, um dieses Fahrzeug zu entfernen?</string>
    <string name="texto_mejor">beste</string>
    <string name="texto_mas_visitada">Am häufigsten besucht</string>
    <string name="mantenimiento_aceite_motor">Motoröl</string>
    <string name="texto_eliminado">Gelöscht</string>
    <string name="mensaje_atencion">Aufmerksamkeit</string>
    <string name="mensaje_no_hay_consumos">Keine Auftanken Für dieses Fahrzeug</string>
    <string name="mensaje_no_hay_gastos">Keine Spesendaten für dieses Fahrzeug</string>
    <string name="mensaje_no_hay_ingresos">Keine Einkommensdaten für dieses Fahrzeug</string>
    <string name="mensaje_no_hay_limpiezas">Keine Reinigungen für dieses Fahrzeug</string>
    <string name="mensaje_no_hay_mantenimientos">Keine Wartung für dieses Fahrzeug</string>
    <string name="mensaje_agregar_consumos_adicionales">Es wird zusätzliche Datensätze Tanken hinzuzufügen. Wollen Sie mit dem Import fortfahren?</string>
    <string name="ingreso_mudanza">Veränderung</string>
    <string name="gasto_multas">Geht Es</string>

    <string name="texto_nombre_archivo">Dateinamen</string>
    <string name="mensaje_widget_no_vehiculo">Keine Fahrzeuge auf diese Widget zuweisen</string>
    <string name="mensaje_no_hay_datos">Keine Daten vorhanden</string>
    <string name="mes_noviembre">November</string>


    <string name="texto_numero_estaciones_servicio">Anzahl der Stationen</string>
    <string name="mes_octubre">Oktober</string>

    <string name="gasto_estacionamiento">Parkplatz</string>


    <string name="texto_peor">Schlechteste</string>
    <string name="texto_desempeño">Leistung</string>
    <string name="mantenimiento_pintura">Malerei</string>
    <string name="texto_precio">Preis</string>

    <string name="mantenimiento_presion_neumaticos">Reifendruck</string>
    <string name="mantenimiento_puertas">Türen</string>
    <string name="texto_volumen_">Volumen(</string>
    <string name="mantenimiento_radiador">Heizkörper</string>
    <string name="recordatorio_proximo_evento">Nächste Veranstaltung</string>
    <string name="recordatorio_titulo">Erinnerung</string>
    <string name="recordatorios">Erinnerungen</string>
    <string name="gasto_remolque">Werg</string>
    <string name="texto_numero_decimales">Anzahl der Dezimalstellen verwendet</string>
    <string name="texto_numero_decimales_precio">Anzahl der Dezimalstellen in Werte der Preise</string>
    <string name="texto_formato_fecha">Datumsformat verwendet</string>
    <string name="texto_unidad_moneda">Währungseinheit verwendet</string>
    <string name="mantenimiento_rines">Räder</string>
    <string name="texto_ruta_autopista">Autobahn</string>
    <string name="texto_ruta_carretera">Straße</string>
    <string name="texto_ruta_ciudad">City</string>
    <string name="texto_ruta_mixta">Gemischt</string>
    <string name="accion_salir">Entfernen</string>
    <string name="texto_redes_sociales">Soziale netzwerke</string>
    <string name="limpieza_secado_a_mano">Handtrocknungs</string>
    <string name="gasto_seguro">Versicherung</string>
    <string name="texto_selecionar_archivo">Wählen Sie die Datei</string>
    <string name="texto_selecionar_vehiculo_widget">Wählen Sie das Fahrzeug für diesen Widget</string>
    <string name="mes_septiembre">September</string>
    <string name="accion_compartir">Teilen</string>
    <string name="texto_soporte">Unterstützung</string>
    <string name="mantenimiento_suspencion">Federungssystem</string>
    <string name="mensaje_borrar_vehiculo">Fahrzeug löschen</string>
    <string name="texto_tiempo">Zeit</string>
    <string name="texto_dias">tage</string>
    <string name="texto_clima_llantas">Wetter/Reifen</string>
    <string name="texto_tipo">Art</string>
    <string name="mensaje_consumo_añadido">Tanken Datensatz hinzugefügt</string>
    <string name="mensaje_consumo_eliminado">Tanken Rekord entfernt</string>
    <string name="mensaje_consumo_actualizado">Tanken Datensatz aktualisiert</string>
    <string name="mensaje_gasto_añadido">Aufwand Datensatz hinzugefügt</string>
    <string name="mensaje_gasto_eliminado">Aufwand Rekord entfernt</string>
    <string name="mensaje_gasto_actualizado">Aufwand Datensatz aktualisiert</string>
    <string name="mensaje_ingreso_añadido">Einkommen Datensatz hinzugefügt</string>
    <string name="mensaje_ingreso_eliminado">Einkommen Rekord entfernt</string>
    <string name="mensaje_ingreso_actualizado">Einkommen Datensatz aktualisiert</string>
    <string name="mensaje_limpieza_añadido">Reinigung Datensatz hinzugefügt</string>
    <string name="mensaje_limpieza_eliminado">Reinigung Rekord entfernt</string>
    <string name="mensaje_limpieza_actualizado">Reinigung Datensatz aktualisiert</string>
    <string name="mensaje_mantenimiento_añadido">Wartung Datensatz hinzugefügt</string>
    <string name="mensaje_mantenimiento_eliminado">Wartung Rekord entfernt</string>
    <string name="mensaje_mantenimiento_actualizado">Wartung Datensatz aktualisiert</string>
    <string name="texto_vehiculo_eliminado">Fahrzeug entfernt</string>
    <string name="texto_total">Gesamt</string>
    <string name="mantenimiento_liquido_transmision">Übertragungsflüssigkeit</string>
    <string name="ingreso_transporte">Verkehr</string>
    <string name="texto_viajes">Trips</string>
    <string name="limpieza_tunel_lavado">Waschstraße</string>
    <string name="mensaje_cargando_copia_seguridad">Backup-Lade</string>

    <string name="texto_selecione_numero_decimales">Wählen Sie die Anzahl der Dezimalstellen</string>
    <string name="texto_seleccione_formato_fecha">Wählen Sie das Datumsformat</string>
    <string name="texto_seleccione_formato_moneda">Wählen Sie eine Währungseinheit</string>
    <string name="texto_cantidad_decimales">Anzahl der Nachkommastellen</string>
    <string name="texto_cantidad_decimales_precio">Dezimal Preis</string>
    <string name="texto_formato">Format</string>
    <string name="texto_unidades">Einheiten</string>

    <string name="texto_version_app">Version</string>
    <string name="mensaje_acerca_app">YeikCar Fahrzeuge ist eine Anwendung, die auf einfache Weise verwaltet, wendig und leistungsstark die verschiedenen Kosten und Einkommen von einem oder mehreren Fahrzeugen, die ein modernes Design und eine intuitive und vollständig und einfaches System, mit dem Sie die Leistung Ihrer Fahrzeuge in die überwachen können kennzeichnet Kraftstoffverbrauch, Wartung, Reinigung, Aufwendungen und Erträge. Neben der Erinnerungsfunktion können einzelne oder wiederkehrende Aufgaben auf dem Fahrzeug durchgeführt, wie Ölwechsel, Reifen, Versicherung Kauf und mehr zu planen! Es hat auch ein voll integriertes Modul von Statistiken und Grafiken, die machen diese Aufgabe sehr viel einfacher werden. </string>
    <string name="texto_ayuda">Hilfe</string>
    <string name="accion_eliminar">Löschen</string>
    <string name="texto_precio_combustible_">Kraftstoffpreis(</string>
    <string name="texto_costo_consumo_">Betankungskosten(</string>
    <string name="texto_configuracion">Einstellungen</string>
    <string name="mensaje_borrar_estacion_servicio">Sind Sie sicher, Sie wollen diesen Service-Station löschen?</string>
    <string name="mensaje_borrar_tipo_gasto">Sind Sie sicher, Sie wollen diesen Aufwandsart zu entfernen?</string>
    <string name="mensaje_borrar_servicio_mantenimiento">Sind Sie sicher, Sie wollen diesen technischen Wartung zu entfernen?</string>
    <string name="texto_borrar_estacion_servicio">Löschen Tankstelle</string>
    <string name="texto_borrar_tipo_gasto">Löschen Aufwandsart</string>
    <string name="texto_borrar_tipo_mantenimiento">Löschen der technischen Wartung</string>
    <string name="mensaje_cargando">Wird Geladen...</string>
    <string name="texto_costo_consumo">BETANKUNGSKOSTEN</string>
    <string name="texto_eficienciaA">EFFIZIENZ</string>
    <string name="texto_costo_combustible">KRAFTSTOFFPREISE</string>
    <string name="texto_volumenN">VOLUME</string>
    <string name="texto_cuarto_trimestre">Im vierten Quartal</string>
    <string name="texto_direccion">Anschrift</string>
    <string name="texto_distancia_por_consumo">Abstand für jedes Tanken</string>
    <string name="accion_editar">Bearbeiten</string>
    <string name="texto_eficiencia">Leistungsfähigkeit</string>
    <string name="texto_copia_seguridad_completada">Sicherung abgeschlossen</string>
    <string name="texto_copia_seguridad_no_completada">Sicherung nicht abgeschlossen</string>
    <string name="mensaje_importar_copia_seguridad">Um eine Sicherungskopie von der Speicherkarte abzurufen, wird dieser Prozess die aktuellen Daten überschreiben möchten Sie weitermachen?</string>
    <string name="texto_importar_base_datos">Importieren von Datenbank</string>
    <string name="accion_listo">Fertig</string>
    <string name="mensaje_error_falta_campos">Vous devez remplir tous les champs nécessaires</string>
    <string name="mensaje_nuevo_tipo_gasto">Geben Sie die neue Art der Ausgaben</string>
    <string name="mensaje_nuevo_tipo_ingreso">Geben Sie die neue Art des Einkommens</string>
    <string name="mensaje_primero_crear_estacion_servicio">Erstellen Sie zunächst eine Tankstelle</string>
    <string name="mensaje_nuevo_tipo_limpieza">Geben Sie die neue Art der Reinigung</string>
    <string name="mensaje_nuevo_nombre_compañia">Geben Sie den Namen des neuen Kraftstoffs Unternehmen</string>
    <string name="mensaje_nuevo_servicio_mantenimiento">Geben Sie den neuen Wartungsservice</string>
    <string name="mensaje_error_faltan_datos">Fehlenden Daten</string>
    <string name="accion_error">Fehler</string>
    <string name="texto_no_hay_estaciones">Kein Service-Station</string>
    <string name="texto_informar_problema">Ein Problem melden</string>
    <string name="texto_estadisticas">Statistik</string>
    <string name="texto_fecha_mayor">Das Datum muss später oder gleich sein</string>
    <string name="texto_fecha_menor">Das Datum muss vor oder gleich zu</string>
    <string name="texto_numero_gastos">Anzahl der Ausgaben</string>
    <string name="texto_gasolinera">Tankstelle</string>
    <string name="texto_historial_cambios">Änderungsverlauf</string>
    <string name="texto_numero_ingresos">Anzahl der Einkommens</string>
    <string name="texto_inventario">Inventar</string>
    <string name="mensaje_mas_tarde">Später</string>
    <string name="texto_kilometraje_mayor">Der Kilometerstand muss höher sein als sein</string>
    <string name="texto_latitud">Breite</string>
    <string name="texto_numero_limpiezas">Anzahl der Reinigungen</string>

    <string name="texto_eficiencia_combustible">Kraftstoffeffizienz</string>
    <string name="texto_moneda">Währung</string>
    <string name="texto_longitud">Länge</string>
    <string name="mensaje_boton_gps">Tippen Sie auf den oberen GPS-Taste, um Ihren Standort zu aktualisieren</string>
    <string name="texto_costos">Kosten</string>
    <string name="texto_consumo">Tanken</string>

    <string name="texto_mantenimiento">Wartung</string>

    <string name="texto_resumen">Zusammenfassung</string>

    <string name="texto_numero_mantenimientos">Anzahl der Wartung</string>
    <string name="mensaje_csv">Sie können den Export oder die tankt dieses Fahrzeugs zu importieren, um eine CSV-Datei (Excel,LibreOffice)</string>
    <string name="mensaje_soporte">Willkommen auf der Support-Bereich YeikCar Fahrzeuge, hier finden Sie Antworten auf die am häufigsten gestellten Fragen über die Anwendung finden, ist die Anwendung noch in der Entwicklung. Ich bin ein einzelner Entwickler und das ist mein Freizeitprojekt. Ich wäre Ihnen dankbar, wenn Sie die PRO-Version gekauft oder dazu beitragen, dieses Projekt mit den folgenden Methoden:</string>
    <string name="texto_consumoO">TANKEN</string>
    <string name="texto_ingresoO">ERTRÄGE</string>
    <string name="texto_limpiezaA">REINIGUNG</string>
    <string name="texto_mantenimientoO">WARTUNG</string>
    <string name="texto_recordatorioO">MAHNUNG</string>
    <string name="texto_gastoO">AUSGABEN</string>
    <string name="mensaje_no_datos_periodo">Im ausgewählten Zeitraum</string>
    <string name="mensaje_no_archivos_disponibles">Noch keine Dateien</string>
    <string name="mensaje_no_datos_periodo_inicial">Keine Aufzeichnungen</string>
    <string name="texto_otros">Andere</string>

    <string name="texto_porcentaje_total">Gesamtprozentsatz</string>
    <string name="texto_primer_trimestre">Erstes Quartal</string>
    <string name="texto_primera_mitad_año">Erstes Halbjahr</string>
    <string name="texto_requerido">Erforderlich(*)</string>
    <string name="texto_correctivo">Korrektive</string>
    <string name="texto_preventivo">Präventiv</string>
    <string name="texto_segundo_trimestre">Zweites Viertel</string>
    <string name="texto_todo_año">Das ganze Jahr</string>
    <string name="texto_servicio_limpieza">Reinigungsservice</string>
    <string name="texto_servicio_mantenimiento">Wartungsservice</string>
    <string name="texto_segunda_mitad_año">Zweites Halbjahr</string>
    <string name="texto_tipo_recordatorio">Kind of Mahnung</string>
    <string name="texto_taller">Werkstatt</string>
    <string name="texto_taller_mecanico">Mechanische Werkstatt</string>
    <string name="texto_tercer_trimestre">Drittes Quartal</string>
    <string name="mensaje_yeikcar_pro">Diese Funktion ist in der Pro-Version. Bitte aktualisieren Sie, um zu entriegeln!</string>
    <string name="texto_traducir">übersetzen</string>
    <string name="texto_descripcion">Beschreibung</string>
    <string name="texto_exterior">äußere</string>
    <string name="texto_volumen">Menge</string>

    <string name="texto_interior">Innere</string>
    <string name="texto_odometro">Kilometerzähler</string>
    <string name="texto_lavado">Waschanlage</string>
    <string name="texto_marca">Marke</string>
    <string name="texto_matricula">Autokennzeichen</string>
    <string name="texto_modelo">Modell</string>
    <string name="texto_nombre">Name</string>
    <string name="texto_nota">Notiz</string>
    <string name="texto_precio_combustible">Kraftstoffpreis</string>
    <string name="texto_gasto">Ausgaben</string>
    <string name="texto_ingreso">Einkommen</string>
    <string name="texto_limpieza">Reinigung</string>

    <string name="texto_servicio">Service</string>
    <string name="texto_tipo_2">Typ</string>
    <string name="texto_tipo_gasto">Arten von Ausgaben</string>
    <string name="texto_tipo_ingreso">Arten von Einkommen</string>
    <string name="texto_costo_total">Gesamtkosten</string>
    <string name="texto_meses">Monat(e)</string>
    <string name="texto_dias_2">Tag(e)</string>
    <string name="texto_años_2">Jahr(e)</string>
    <string name="texto_valor_maximo">Höchstwert</string>
    <string name="texto_valor_minimo">Minimalwert</string>
    <string name="texto_valor_promedio">Mittelwert</string>
    <string name="texto_visor_csv">CSV-Viewer</string>
    <string name="app_name">YeikCar</string>
    <string name="texto_almacen">Geschäft</string>
    <string name="texto_telefono">Telefon</string>
    <string name="texto_lugar">Ort</string>
    <string name="texto_recordatorio_vencido">Abgelaufen</string>
    <string name="texto_recordatorio_activo">Aktiv</string>
    <string name="texto_recordatorio_pendiente">Anhängig</string>
    <string name="texto_recordatorio_todos">Alle</string>
    <string name="texto_faq">Häufig gestellte Fragen</string>
    <string name="mensaje_enviar_sugerencias">Feedback schicken</string>
    <string name="mensaje_no_funcionando">Etwas nicht funktioniert</string>
    <string name="mensaje_sugerir_idea">Funktion vorschlagen</string>
    <string name="texto_se_repite_cada">Es wird jeden wiederholt</string>
    <string name="mensaje_nada_pendiente">Es gibt nichts anhängigen</string>
    <string name="mensaje_no_recordatorios_activos">Keine aktiven mahnungen</string>
    <string name="mantenimiento_frenos_delanteros">Bremsen vorne</string>
    <string name="mantenimiento_frenos_traseros">Bremsen hinten</string>
    <string name="mantenimiento_filtro_cabina">Innenraumluftfilter</string>
    <string name="mantenimiento_filtro_aire">Luftfilter</string>
    <string name="mantenimiento_liquido_diferencial">Differentialflüssigkeits</string>
    <string name="mantenimiento_sistema_escape">Abgasanlage</string>
    <string name="mantenimiento_bomba_combustible">Benzinpumpe</string>
    <string name="mantenimiento_filtro_aceite">Ölfilter</string>
    <string name="mantenimiento_liquido_hidraulica">Servolenkungsflüssigkeit</string>
    <string name="texto_solo_una_vez">Nur einmal</string>
    <string name="texto_repetidamente">Repetitiven schleife</string>
    <string name="recordatorio_activo">Erinnerung Daran Aktiviert</string>
    <string name="texto_recordatorio_no_activo">Erinnerung nicht aktiviert</string>
    <string name="texto_marcar_completado">Als erledigt markieren?</string>
    <string name="accion_ahora">Jetzt!</string>
    <string name="accion_ignorar">Ignorieren</string>
    <string name="mensaje_ignorar">Sind Sie sicher, dass Sie diese Erinnerung zu ignorieren?</string>
    <string name="accion_si">Ja</string>
    <string name="accion_no">Nein</string>
    <string name="reportes_saldo">Kontostand</string>
    <string name="texto_gastos_ingresos">Aufwendungen/Erträge</string>
    <string name="texto_intro_1">Halten Sie ein detailliertes Protokoll aller Aktivitäten Ihres Fahrzeugs</string>
    <string name="texto_intro_2">Nie wieder werden Sie etwas Wichtiges aus Ihrem Fahrzeug vergessen.</string>
    <string name="texto_reportes">Berichte</string>
    <string name="mensaje_no_se_puede_eliminar">Der Datensatz kann nicht gelöscht werden</string>
    <string name="texto_yeikcar_pro">Einige Funktionen dieser Anwendung ist nur mit der Pro-Version</string>
    <string name="accion_comprar">Kaufen</string>

    <string name="texto_permiso_denegado">Erlaubnis verweigert</string>
    <string name="mensaje_permiso_ubicacion_necesaria">Sie müssen Zugang zu Standort ermöglichen</string>
    <string name="mensaje_permiso_storage_necesaria">Sie müssen Zugriff auf Speicher erlauben</string>
    <string name="mensaje_keep">Halten Sie es von der Leistung Ihres Fahrzeugs informiert</string>
    <string name="texto_tanque">Tank</string>
    <string name="texto_lleno">Voll</string>
    <string name="texto_parcial">Teilweise</string>
    <string name="mensaje_perdido">Vorheriges volltanken verpasst</string>
    <string name="texto_perdido">Verpasst</string>
    <string name="texto_mismo_odometro">Wiederholt Kilometerstand</string>
    <string name="mensaje_diferente_cero">Der wert der distanz und zeit kann nicht Null sein</string>
    <string name="texto_yeikcar_pro_detalles">• Unbegrenzte Fahrzeuge \n • Unbegrenzte erinnerungen \n • Unbegrenzte bestandsaufnahme \n • Bearbeiten von bestandsaufnahme  \n • Datensicherung Dropbox  \n • Export CSV Fahrzeugberichte (* Excel)   \n • Details zu Berichten Leistung</string>
    <string name="accion_gracias">Vielen Dank für den Kauf</string>
    <string name="accion_inactivo">Inaktiv</string>
    <string name="accion_saltar">Überspringen</string>
    <string name="accion_visitar">Besuche</string>
    <string name="texto_estado">Status</string>
    <string name="texto_mapa_satelital">SATELLITE</string>
    <string name="texto_mapa_hibrido">HYBRID</string>
    <string name="texto_tema">Farbschema</string>
    <string name="texto_estilo">App-Design</string>
    <string name="texto_intervalo_grafica">Charts Intervall</string>
    <string name="texto_resumen_grafica">Anzahl der Proben graphisch dargestellt werden</string>
    <string name="texto_unidad_grafica">Punkte graphisch dargestellt werden</string>
    <string name="texto_semanas">Wochen</string>
    <string name="texto_desde_principio">Von Anfang an</string>
    <string name="texto_ultimos">Letzten</string>
    <string name="gasto_peajes">Maut</string>


</resources>